simple_threadpool.py
simple_threadpool-1.0.0.dist-info/METADATA
simple_threadpool-1.0.0.dist-info/WHEEL
simple_threadpool-1.0.0.dist-info/top_level.txt
simple_threadpool-1.0.0.dist-info/RECORD
