Metadata-Version: 2.1
Name: simple-threadpool
Version: 1.0.0
Summary: A simple threadpool
Home-page: https://github.com/ichuan/simple_threadpool
Author: yc
Author-email: 
License: MIT
Platform: UNKNOWN
Classifier: License :: OSI Approved :: MIT License
Classifier: Programming Language :: Python
Classifier: Programming Language :: Python :: 2
Classifier: Programming Language :: Python :: 3
Classifier: Programming Language :: Python :: Implementation :: CPython
Classifier: Programming Language :: Python :: Implementation :: PyPy
Requires-Python: >=2.6.0
